healthchecks_decorator/__init__.py
healthchecks_decorator/decorator.py
healthchecks_decorator/py.typed
healthchecks_decorator-0.5.0.dist-info/entry_points.txt
healthchecks_decorator-0.5.0.dist-info/LICENSE.rst
healthchecks_decorator-0.5.0.dist-info/WHEEL
healthchecks_decorator-0.5.0.dist-info/METADATA
healthchecks_decorator-0.5.0.dist-info/RECORD
