Metadata-Version: 2.1
Name: healthchecks-decorator
Version: 0.5.0
Summary: Healthchecks Decorator
Home-page: https://github.com/danidelvalle/healthchecks-decorator
License: MIT
Author: Daniel del Valle
Author-email: delvalle.dani@gmail.com
Requires-Python: >=3.8,<4.0
Classifier: Development Status :: 3 - Alpha
Classifier: License :: OSI Approved :: MIT License
Classifier: Programming Language :: Python :: 3
Classifier: Programming Language :: Python :: 3.8
Classifier: Programming Language :: Python :: 3.9
Classifier: Programming Language :: Python :: 3.10
Classifier: Programming Language :: Python :: 3.11
Project-URL: Changelog, https://github.com/danidelvalle/healthchecks-decora|/releases
Project-URL: Documentation, https://healthchecks-decorator.readthedocs.io
Project-URL: Repository, https://github.com/danidelvalle/healthchecks-decorator
